{
    "meta_data": [
        {
            "config": {
                "DBM": true,
                "continue_training": false,
                "task_id": "001",
                "envs_NK": [
                    [
                        2,
                        2
                    ],
                    [
                        2,
                        3
                    ]
                ],
                "use_pretrained_model": false,
                "pretrained_model_id": "None",
                "new_ineq_num_factor": 0.5,
                "log_dir": "02all_data/001",
                "num_worker": 1,
                "about_training": "\u4e0d\u77e5\u9053\u600e\u4e48\u56de\u4e8b\uff0c\u4f46\u662f\u68af\u5ea6\u66f4\u65b0\u7684\u65b9\u5411\u786e\u5b9e\u662f\u53cd\u7740\u7684\u3002\u5c1d\u8bd5\u4fee\u6539\u4e00\u4e0b\u54ce\n **   ** \n**** ****\n*********\n *******\n  *****\n   ***\n    *",
                "max_rollout_num": 1000,
                "n_directions": 4,
                "evaluate_time": 3,
                "learning_rate": 0.01,
                "gamma": 0.97,
                "std": 0.02,
                "rollout_length": 10,
                "network_param": {
                    "hsize": 64,
                    "numlayers": 2,
                    "embed": 100,
                    "numvars": 383
                },
                "device": "cuda"
            },
            "start_time": "2025-08-03 13:58:17",
            "start_time_in_seconds": 1754200697.9701738,
            "end_time": null,
            "end_time_in_seconds": null
        }
    ],
    "evaluate_average_rewards": [
        0.0,
        0.0,
        0.0,
        0.0,
        0.0,
        0.0,
        0.0,
        0.0,
        0.0,
        0.0
    ],
    "clocktime": [
        26.83021378517151,
        25.02585792541504,
        24.645514011383057,
        24.996856927871704,
        27.42850089073181,
        51.8037211894989,
        29.021522045135498,
        25.981223344802856,
        25.956997871398926,
        25.988770961761475
    ],
    "results": [
        [
            [
                0,
                [
                    0.0,
                    0.0
                ],
                [
                    5,
                    5
                ]
            ],
            [
                1,
                [
                    0.0,
                    0.0
                ],
                [
                    5,
                    5
                ]
            ],
            [
                2,
                [
                    0.0,
                    0.0
                ],
                [
                    5,
                    5
                ]
            ],
            [
                3,
                [
                    0.0,
                    0.0
                ],
                [
                    5,
                    5
                ]
            ],
            [
                4,
                [
                    0.0,
                    0.0
                ],
                [
                    5,
                    5
                ]
            ],
            [
                5,
                [
                    0.0,
                    0.0
                ],
                [
                    5,
                    5
                ]
            ],
            [
                6,
                [
                    0.0,
                    0.0
                ],
                [
                    5,
                    5
                ]
            ]
        ],
        [
            [
                0,
                [
                    0.0,
                    0.0
                ],
                [
                    5,
                    5
                ]
            ],
            [
                1,
                [
                    0.0,
                    0.0
                ],
                [
                    5,
                    5
                ]
            ],
            [
                2,
                [
                    0.0,
                    0.0
                ],
                [
                    5,
                    5
                ]
            ],
            [
                3,
                [
                    0.0,
                    0.0
                ],
                [
                    5,
                    5
                ]
            ],
            [
                4,
                [
                    0.0,
                    0.0
                ],
                [
                    5,
                    5
                ]
            ],
            [
                5,
                [
                    0.0,
                    0.0
                ],
                [
                    5,
                    5
                ]
            ],
            [
                6,
                [
                    0.0,
                    0.0
                ],
                [
                    5,
                    5
                ]
            ]
        ],
        [
            [
                0,
                [
                    0.0,
                    0.0
                ],
                [
                    5,
                    5
                ]
            ],
            [
                1,
                [
                    0.0,
                    0.0
                ],
                [
                    5,
                    5
                ]
            ],
            [
                2,
                [
                    0.0,
                    0.0
                ],
                [
                    5,
                    5
                ]
            ],
            [
                3,
                [
                    0.0,
                    0.0
                ],
                [
                    5,
                    5
                ]
            ],
            [
                4,
                [
                    0.0,
                    0.0
                ],
                [
                    5,
                    5
                ]
            ],
            [
                5,
                [
                    0.0,
                    0.0
                ],
                [
                    5,
                    5
                ]
            ],
            [
                6,
                [
                    0.0,
                    0.0
                ],
                [
                    5,
                    5
                ]
            ]
        ],
        [
            [
                0,
                [
                    0.0,
                    0.0
                ],
                [
                    5,
                    5
                ]
            ],
            [
                1,
                [
                    0.0,
                    0.0
                ],
                [
                    5,
                    5
                ]
            ],
            [
                2,
                [
                    0.0,
                    0.0
                ],
                [
                    5,
                    5
                ]
            ],
            [
                3,
                [
                    0.0,
                    0.0
                ],
                [
                    5,
                    5
                ]
            ],
            [
                4,
                [
                    0.0,
                    0.0
                ],
                [
                    5,
                    5
                ]
            ],
            [
                5,
                [
                    0.0,
                    0.0
                ],
                [
                    5,
                    5
                ]
            ],
            [
                6,
                [
                    0.0,
                    0.0
                ],
                [
                    5,
                    5
                ]
            ]
        ],
        [
            [
                0,
                [
                    0.0,
                    0.0
                ],
                [
                    5,
                    5
                ]
            ],
            [
                1,
                [
                    0.0,
                    0.0
                ],
                [
                    5,
                    5
                ]
            ],
            [
                2,
                [
                    0.0,
                    0.0
                ],
                [
                    5,
                    5
                ]
            ],
            [
                3,
                [
                    0.0,
                    0.0
                ],
                [
                    5,
                    5
                ]
            ],
            [
                4,
                [
                    0.0,
                    0.0
                ],
                [
                    5,
                    5
                ]
            ],
            [
                5,
                [
                    0.0,
                    0.0
                ],
                [
                    5,
                    5
                ]
            ],
            [
                6,
                [
                    0.0,
                    0.0
                ],
                [
                    5,
                    5
                ]
            ]
        ],
        [
            [
                0,
                [
                    0.0,
                    0.0
                ],
                [
                    5,
                    5
                ]
            ],
            [
                1,
                [
                    0.0,
                    0.0
                ],
                [
                    5,
                    5
                ]
            ],
            [
                2,
                [
                    0.0,
                    0.0
                ],
                [
                    5,
                    5
                ]
            ],
            [
                3,
                [
                    0.0,
                    0.0
                ],
                [
                    5,
                    5
                ]
            ],
            [
                4,
                [
                    0.0,
                    0.0
                ],
                [
                    5,
                    5
                ]
            ],
            [
                5,
                [
                    0.0,
                    0.0
                ],
                [
                    5,
                    5
                ]
            ],
            [
                6,
                [
                    0.0,
                    0.0
                ],
                [
                    5,
                    5
                ]
            ]
        ],
        [
            [
                0,
                [
                    0.0,
                    0.0
                ],
                [
                    5,
                    5
                ]
            ],
            [
                1,
                [
                    0.0,
                    0.0
                ],
                [
                    5,
                    5
                ]
            ],
            [
                2,
                [
                    0.0,
                    0.0
                ],
                [
                    5,
                    5
                ]
            ],
            [
                3,
                [
                    0.0,
                    0.0
                ],
                [
                    5,
                    5
                ]
            ],
            [
                4,
                [
                    0.0,
                    0.0
                ],
                [
                    5,
                    5
                ]
            ],
            [
                5,
                [
                    0.0,
                    0.0
                ],
                [
                    5,
                    5
                ]
            ],
            [
                6,
                [
                    0.0,
                    0.0
                ],
                [
                    5,
                    5
                ]
            ]
        ],
        [
            [
                0,
                [
                    0.0,
                    0.0
                ],
                [
                    5,
                    5
                ]
            ],
            [
                1,
                [
                    0.0,
                    0.0
                ],
                [
                    5,
                    5
                ]
            ],
            [
                2,
                [
                    0.0,
                    0.0
                ],
                [
                    5,
                    5
                ]
            ],
            [
                3,
                [
                    0.0,
                    0.0
                ],
                [
                    5,
                    5
                ]
            ],
            [
                4,
                [
                    0.0,
                    0.0
                ],
                [
                    5,
                    5
                ]
            ],
            [
                5,
                [
                    0.0,
                    0.0
                ],
                [
                    5,
                    5
                ]
            ],
            [
                6,
                [
                    0.0,
                    0.0
                ],
                [
                    5,
                    5
                ]
            ]
        ],
        [
            [
                0,
                [
                    0.0,
                    0.0
                ],
                [
                    5,
                    5
                ]
            ],
            [
                1,
                [
                    0.0,
                    0.0
                ],
                [
                    5,
                    5
                ]
            ],
            [
                2,
                [
                    0.0,
                    0.0
                ],
                [
                    5,
                    5
                ]
            ],
            [
                3,
                [
                    0.0,
                    0.0
                ],
                [
                    5,
                    5
                ]
            ],
            [
                4,
                [
                    0.0,
                    0.0
                ],
                [
                    5,
                    5
                ]
            ],
            [
                5,
                [
                    0.0,
                    0.0
                ],
                [
                    5,
                    5
                ]
            ],
            [
                6,
                [
                    0.0,
                    0.0
                ],
                [
                    5,
                    5
                ]
            ]
        ],
        [
            [
                0,
                [
                    0.0,
                    0.0
                ],
                [
                    5,
                    5
                ]
            ],
            [
                1,
                [
                    0.0,
                    0.0
                ],
                [
                    5,
                    5
                ]
            ],
            [
                2,
                [
                    0.0,
                    0.0
                ],
                [
                    5,
                    5
                ]
            ],
            [
                3,
                [
                    0.0,
                    0.0
                ],
                [
                    5,
                    5
                ]
            ],
            [
                4,
                [
                    0.0,
                    0.0
                ],
                [
                    5,
                    5
                ]
            ],
            [
                5,
                [
                    0.0,
                    0.0
                ],
                [
                    5,
                    5
                ]
            ],
            [
                6,
                [
                    0.0,
                    0.0
                ],
                [
                    5,
                    5
                ]
            ]
        ]
    ],
    "evaluate_each_rewards": [
        [
            [
                0.0,
                0.0
            ],
            [
                0.0,
                0.0
            ],
            [
                0.0,
                0.0
            ]
        ],
        [
            [
                0.0,
                0.0
            ],
            [
                0.0,
                0.0
            ],
            [
                0.0,
                0.0
            ]
        ],
        [
            [
                0.0,
                0.0
            ],
            [
                0.0,
                0.0
            ],
            [
                0.0,
                0.0
            ]
        ],
        [
            [
                0.0,
                0.0
            ],
            [
                0.0,
                0.0
            ],
            [
                0.0,
                0.0
            ]
        ],
        [
            [
                0.0,
                0.0
            ],
            [
                0.0,
                0.0
            ],
            [
                0.0,
                0.0
            ]
        ],
        [
            [
                0.0,
                0.0
            ],
            [
                0.0,
                0.0
            ],
            [
                0.0,
                0.0
            ]
        ],
        [
            [
                0.0,
                0.0
            ],
            [
                0.0,
                0.0
            ],
            [
                0.0,
                0.0
            ]
        ],
        [
            [
                0.0,
                0.0
            ],
            [
                0.0,
                0.0
            ],
            [
                0.0,
                0.0
            ]
        ],
        [
            [
                0.0,
                0.0
            ],
            [
                0.0,
                0.0
            ],
            [
                0.0,
                0.0
            ]
        ],
        [
            [
                0.0,
                0.0
            ],
            [
                0.0,
                0.0
            ],
            [
                0.0,
                0.0
            ]
        ]
    ],
    "evaluate_env_rewards": [
        [
            0.0,
            0.0
        ],
        [
            0.0,
            0.0
        ],
        [
            0.0,
            0.0
        ],
        [
            0.0,
            0.0
        ],
        [
            0.0,
            0.0
        ],
        [
            0.0,
            0.0
        ],
        [
            0.0,
            0.0
        ],
        [
            0.0,
            0.0
        ],
        [
            0.0,
            0.0
        ],
        [
            0.0,
            0.0
        ]
    ],
    "rollout_time": [
        26.748729705810547,
        25.020857572555542,
        24.64002299308777,
        24.98985719680786,
        27.421499252319336,
        51.79272222518921,
        29.0155246257782,
        25.974211931228638,
        25.947996139526367,
        25.981118202209473
    ]
}